records2/__init__.py
records2/async_database.py
records2/database.py
records2/record.py
records2/utils.py
records2-1.0.0.dist-info/METADATA
records2-1.0.0.dist-info/WHEEL
records2-1.0.0.dist-info/RECORD
