Metadata-Version: 2.4
Name: records2
Version: 1.0.0
Summary: A comprehensive, type-safe database solution for Python
Author-email: Chidebele Dunamis <techwithdunamix@gmail.com>
License-Expression: BSD-3-Clause
Keywords: async,database,nexios,python,records,sqlite,type-safe
Requires-Python: >=3.9
Requires-Dist: aiosqlite
Requires-Dist: sqlalchemy
Requires-Dist: tablib
Provides-Extra: asyncpg
Requires-Dist: asyncpg>=0.27.0; extra == 'asyncpg'
Provides-Extra: dev
Requires-Dist: black>=23.0.0; extra == 'dev'
Requires-Dist: isort>=5.12.0; extra == 'dev'
Requires-Dist: pytest-asyncio>=0.25.3; extra == 'dev'
Requires-Dist: pytest>=8.3.4; extra == 'dev'
